pytest_unused_port/__init__.py
pytest_unused_port/__main__.py
pytest_unused_port-0.2.dist-info/licenses/LICENSE
pytest_unused_port-0.2.dist-info/METADATA
pytest_unused_port-0.2.dist-info/WHEEL
pytest_unused_port-0.2.dist-info/entry_points.txt
pytest_unused_port-0.2.dist-info/top_level.txt
pytest_unused_port-0.2.dist-info/RECORD
