Metadata-Version: 2.4
Name: pytest-unused-port
Version: 0.2
Summary: pytest fixture finding an unused local port
Author: Simon Willison
License-Expression: Apache-2.0
Project-URL: Homepage, https://github.com/simonw/pytest-unused-port
Project-URL: Changelog, https://github.com/simonw/pytest-unused-port/releases
Project-URL: Issues, https://github.com/simonw/pytest-unused-port/issues
Project-URL: CI, https://github.com/simonw/pytest-unused-port/actions
Classifier: Framework :: Pytest
Requires-Python: >=3.10
License-File: LICENSE
Requires-Dist: pytest
Dynamic: license-file
